pyfund/__init__.py
pyfund/api.py
pyfund/backtesting.py
pyfund/cli.py
pyfund/cmds/__init__.py
pyfund/cmds/backtest.py
pyfund/cmds/corrcoef.py
pyfund/cmds/etf.py
pyfund/cmds/fund_bond.py
pyfund/cmds/fund_index.py
pyfund/cmds/fund_mix.py
pyfund/cmds/init.py
pyfund/cmds/init_fund.py
pyfund/cmds/status.py
pyfund/cmds/stock.py
pyfund/cmds/stocks.py
pyfund/cmds/test.py
pyfund/constants.py
pyfund/core.py
pyfund/net/README.md
pyfund/net/__init__.py
pyfund/net/csindex.py
pyfund/net/eastmoney.py
pyfund/net/investing.py
pyfund/net/lixinger.py
pyfund/net/qieman.py
pyfund/net/sina.py
pyfund/net/xueqiu.py
pyfund/net/yahoo.py
pyfund/strategies/__init__.py
pyfund/strategies/bull.py
pyfund/strategies/day.py
pyfund/strategies/week.py
pyfund/strategy.py
pyfund/utils.py
pyfund-0.1.1.dist-info/entry_points.txt
pyfund-0.1.1.dist-info/LICENSE
pyfund-0.1.1.dist-info/WHEEL
pyfund-0.1.1.dist-info/METADATA
pyfund-0.1.1.dist-info/RECORD
