Metadata-Version: 2.1
Name: pyfund
Version: 0.1.1
Summary: 
Author: kin9-0rz
Author-email: kin9-0rz@outlook.com
Requires-Python: >=3.7.1,<3.11
Classifier: Programming Language :: Python :: 3
Classifier: Programming Language :: Python :: 3.10
Classifier: Programming Language :: Python :: 3.8
Classifier: Programming Language :: Python :: 3.9
Requires-Dist: akshare (>=1.1.94,<2.0.0)
Requires-Dist: arrow (>=1.2.1,<2.0.0)
Requires-Dist: click (>=8.0.3,<9.0.0)
Requires-Dist: decorator (>=5.1.0,<6.0.0)
Requires-Dist: html5lib (>=1.1,<2.0)
Requires-Dist: kiwisolver (>=1.3.2,<2.0.0)
Requires-Dist: numpy (>=1.21.3,<2.0.0)
Requires-Dist: pandas (>=1.3.4,<2.0.0)
Requires-Dist: petty (>=0.1.1,<0.2.0)
Requires-Dist: py-mini-racer (>=0.6.0,<0.7.0)
Requires-Dist: pyparsing (>=3.0.4,<4.0.0)
Requires-Dist: requests (>=2.26.0,<3.0.0)
Requires-Dist: rich (>=10.12.0,<11.0.0)
Requires-Dist: selectolax (>=0.3.5,<0.4.0)
Requires-Dist: six (>=1.16.0,<2.0.0)
Requires-Dist: tabulate (>=0.8.9,<0.9.0)
Requires-Dist: toml (>=0.10.2,<0.11.0)
